{"5.12": {"0.0": {"precision": 0.0, "recall": 0.0, "f1-score": 0.0, "support": 0}, "0.25": {"precision": 0.0, "recall": 0.0, "f1-score": 0.0, "support": 0}, "0.5": {"precision": 0.0, "recall": 0.0, "f1-score": 0.0, "support": 0}, "0.75": {"precision": 0.0, "recall": 0.0, "f1-score": 0.0, "support": 0}, "1.0": {"precision": 1.0, "recall": 0.08333333333333333, "f1-score": 0.15384615384615385, "support": 12}, "1.25": {"precision": 0.0, "recall": 0.0, "f1-score": 0.0, "support": 0}, "2.0": {"precision": 0.0, "recall": 0.0, "f1-score": 0.0, "support": 0}, "2.75": {"precision": 0.0, "recall": 0.0, "f1-score": 0.0, "support": 0}, "accuracy": 0.08333333333333333, "macro avg": {"precision": 0.125, "recall": 0.010416666666666666, "f1-score": 0.019230769230769232, "support": 12}, "weighted avg": {"precision": 1.0, "recall": 0.08333333333333333, "f1-score": 0.15384615384615385, "support": 12}}, "5.11": {"0.0": {"precision": 0.0, "recall": 0.0, "f1-score": 0.0, "support": 0.0}, "0.5": {"precision": 0.0, "recall": 0.0, "f1-score": 0.0, "support": 1.0}, "1.0": {"precision": 0.0, "recall": 0.0, "f1-score": 0.0, "support": 22.0}, "accuracy": 0.0, "macro avg": {"precision": 0.0, "recall": 0.0, "f1-score": 0.0, "support": 23.0}, "weighted avg": {"precision": 0.0, "recall": 0.0, "f1-score": 0.0, "support": 23.0}}, "4.3_LM": {"0.0": {"precision": 0.0, "recall": 0.0, "f1-score": 0.0, "support": 0.0}, "0.5": {"precision": 0.0, "recall": 0.0, "f1-score": 0.0, "support": 1.0}, "1.0": {"precision": 0.0, "recall": 0.0, "f1-score": 0.0, "support": 9.0}, "accuracy": 0.0, "macro avg": {"precision": 0.0, "recall": 0.0, "f1-score": 0.0, "support": 10.0}, "weighted avg": {"precision": 0.0, "recall": 0.0, "f1-score": 0.0, "support": 10.0}}, "11.4_SDN": {"accuracy": 0.0, "macro avg": {"precision": NaN, "recall": NaN, "f1-score": NaN, "support": 0.0}, "weighted avg": {"precision": 0.0, "recall": 0.0, "f1-score": 0.0, "support": 0.0}}, "12.2_PE": {"0.0": {"precision": 0.4444444444444444, "recall": 1.0, "f1-score": 0.6153846153846153, "support": 4}, "0.25": {"precision": 0.0, "recall": 0.0, "f1-score": 0.0, "support": 1}, "0.5": {"precision": 0.0, "recall": 0.0, "f1-score": 0.0, "support": 1}, "1.0": {"precision": 0.0, "recall": 0.0, "f1-score": 0.0, "support": 4}, "accuracy": 0.4, "macro avg": {"precision": 0.1111111111111111, "recall": 0.25, "f1-score": 0.15384615384615383, "support": 10}, "weighted avg": {"precision": 0.17777777777777776, "recall": 0.4, "f1-score": 0.2461538461538461, "support": 10}}, "10.2_TC": {"0.0": {"precision": 0.0, "recall": 0.0, "f1-score": 0.0, "support": 0}, "0.25": {"precision": 0.2, "recall": 1.0, "f1-score": 0.33333333333333337, "support": 1}, "0.375": {"precision": 0.0, "recall": 0.0, "f1-score": 0.0, "support": 1}, "0.5": {"precision": 0.0, "recall": 0.0, "f1-score": 0.0, "support": 1}, "0.625": {"precision": 0.0, "recall": 0.0, "f1-score": 0.0, "support": 1}, "0.75": {"precision": 0.0, "recall": 0.0, "f1-score": 0.0, "support": 5}, "1.0": {"precision": 0.0, "recall": 0.0, "f1-score": 0.0, "support": 2}, "accuracy": 0.09090909090909091, "macro avg": {"precision": 0.028571428571428574, "recall": 0.14285714285714285, "f1-score": 0.04761904761904762, "support": 11}, "weighted avg": {"precision": 0.018181818181818184, "recall": 0.09090909090909091, "f1-score": 0.030303030303030307, "support": 11}}, "2.1_DLL_v1.1": {"0.0": {"precision": 0.0, "recall": 0.0, "f1-score": 0.0, "support": 0.0}, "0.25": {"precision": 0.0, "recall": 0.0, "f1-score": 0.0, "support": 0.0}, "0.5": {"precision": 0.0, "recall": 0.0, "f1-score": 0.0, "support": 0.0}, "0.75": {"precision": 0.0, "recall": 0.0, "f1-score": 0.0, "support": 0.0}, "1.0": {"precision": 0.0, "recall": 0.0, "f1-score": 0.0, "support": 15.0}, "accuracy": 0.0, "macro avg": {"precision": 0.0, "recall": 0.0, "f1-score": 0.0, "support": 15.0}, "weighted avg": {"precision": 0.0, "recall": 0.0, "f1-score": 0.0, "support": 15.0}}, "8.3_MM": {"0.0": {"precision": 0.0, "recall": 0.0, "f1-score": 0.0, "support": 0.0}, "0.25": {"precision": 0.0, "recall": 0.0, "f1-score": 0.0, "support": 2.0}, "0.5": {"precision": 0.0, "recall": 0.0, "f1-score": 0.0, "support": 5.0}, "1.0": {"precision": 0.0, "recall": 0.0, "f1-score": 0.0, "support": 3.0}, "accuracy": 0.0, "macro avg": {"precision": 0.0, "recall": 0.0, "f1-score": 0.0, "support": 10.0}, "weighted avg": {"precision": 0.0, "recall": 0.0, "f1-score": 0.0, "support": 10.0}}, "8.1_MM": {"0.0": {"precision": 0.0, "recall": 0.0, "f1-score": 0.0, "support": 1.0}, "0.25": {"precision": 0.0, "recall": 0.0, "f1-score": 0.0, "support": 1.0}, "0.5": {"precision": 0.0, "recall": 0.0, "f1-score": 0.0, "support": 0.0}, "0.75": {"precision": 0.0, "recall": 0.0, "f1-score": 0.0, "support": 1.0}, "0.875": {"precision": 0.0, "recall": 0.0, "f1-score": 0.0, "support": 2.0}, "1.0": {"precision": 0.0, "recall": 0.0, "f1-score": 0.0, "support": 11.0}, "accuracy": 0.0, "macro avg": {"precision": 0.0, "recall": 0.0, "f1-score": 0.0, "support": 16.0}, "weighted avg": {"precision": 0.0, "recall": 0.0, "f1-score": 0.0, "support": 16.0}}, "4.1_LM_v1.0": {"0.0": {"precision": 0.0, "recall": 0.0, "f1-score": 0.0, "support": 0.0}, "0.5": {"precision": 0.0, "recall": 0.0, "f1-score": 0.0, "support": 0.0}, "1.0": {"precision": 0.0, "recall": 0.0, "f1-score": 0.0, "support": 16.0}, "accuracy": 0.0, "macro avg": {"precision": 0.0, "recall": 0.0, "f1-score": 0.0, "support": 16.0}, "weighted avg": {"precision": 0.0, "recall": 0.0, "f1-score": 0.0, "support": 16.0}}, "6.3": {"0.0": {"precision": 0.0, "recall": 0.0, "f1-score": 0.0, "support": 0.0}, "0.125": {"precision": 0.0, "recall": 0.0, "f1-score": 0.0, "support": 0.0}, "0.25": {"precision": 0.0, "recall": 0.0, "f1-score": 0.0, "support": 1.0}, "0.375": {"precision": 0.0, "recall": 0.0, "f1-score": 0.0, "support": 0.0}, "0.5": {"precision": 0.0, "recall": 0.0, "f1-score": 0.0, "support": 0.0}, "0.625": {"precision": 0.0, "recall": 0.0, "f1-score": 0.0, "support": 2.0}, "0.75": {"precision": 0.0, "recall": 0.0, "f1-score": 0.0, "support": 5.0}, "0.875": {"precision": 0.0, "recall": 0.0, "f1-score": 0.0, "support": 14.0}, "1.0": {"precision": 0.0, "recall": 0.0, "f1-score": 0.0, "support": 2.0}, "accuracy": 0.0, "macro avg": {"precision": 0.0, "recall": 0.0, "f1-score": 0.0, "support": 24.0}, "weighted avg": {"precision": 0.0, "recall": 0.0, "f1-score": 0.0, "support": 24.0}}, "2.4": {"0.0": {"precision": 0.0, "recall": 0.0, "f1-score": 0.0, "support": 0.0}, "0.375": {"precision": 0.0, "recall": 0.0, "f1-score": 0.0, "support": 1.0}, "0.5": {"precision": 0.0, "recall": 0.0, "f1-score": 0.0, "support": 0.0}, "0.75": {"precision": 0.0, "recall": 0.0, "f1-score": 0.0, "support": 2.0}, "0.875": {"precision": 0.0, "recall": 0.0, "f1-score": 0.0, "support": 3.0}, "1.0": {"precision": 0.0, "recall": 0.0, "f1-score": 0.0, "support": 11.0}, "1.5": {"precision": 0.0, "recall": 0.0, "f1-score": 0.0, "support": 0.0}, "accuracy": 0.0, "macro avg": {"precision": 0.0, "recall": 0.0, "f1-score": 0.0, "support": 17.0}, "weighted avg": {"precision": 0.0, "recall": 0.0, "f1-score": 0.0, "support": 17.0}}, "4.13": {"0.0": {"precision": 0.125, "recall": 1.0, "f1-score": 0.2222222222222222, "support": 1}, "0.25": {"precision": 0.0, "recall": 0.0, "f1-score": 0.0, "support": 0}, "0.5": {"precision": 0.0, "recall": 0.0, "f1-score": 0.0, "support": 2}, "0.75": {"precision": 1.0, "recall": 0.25, "f1-score": 0.4, "support": 4}, "1.0": {"precision": 0.0, "recall": 0.0, "f1-score": 0.0, "support": 6}, "accuracy": 0.15384615384615385, "macro avg": {"precision": 0.225, "recall": 0.25, "f1-score": 0.12444444444444444, "support": 13}, "weighted avg": {"precision": 0.3173076923076923, "recall": 0.15384615384615385, "f1-score": 0.14017094017094017, "support": 13}}, "10.1_TC": {"0.0": {"precision": 0.0, "recall": 0.0, "f1-score": 0.0, "support": 2}, "0.25": {"precision": 0.0, "recall": 0.0, "f1-score": 0.0, "support": 0}, "0.75": {"precision": 0.0, "recall": 0.0, "f1-score": 0.0, "support": 0}, "0.875": {"precision": 0.0, "recall": 0.0, "f1-score": 0.0, "support": 1}, "1.0": {"precision": 1.0, "recall": 0.1111111111111111, "f1-score": 0.19999999999999998, "support": 9}, "1.25": {"precision": 0.0, "recall": 0.0, "f1-score": 0.0, "support": 0}, "1.5": {"precision": 0.0, "recall": 0.0, "f1-score": 0.0, "support": 0}, "1.75": {"precision": 0.0, "recall": 0.0, "f1-score": 0.0, "support": 0}, "2.25": {"precision": 0.0, "recall": 0.0, "f1-score": 0.0, "support": 0}, "accuracy": 0.08333333333333333, "macro avg": {"precision": 0.1111111111111111, "recall": 0.012345679012345678, "f1-score": 0.02222222222222222, "support": 12}, "weighted avg": {"precision": 0.75, "recall": 0.08333333333333333, "f1-score": 0.15, "support": 12}}, "6.1_IPP": {"0.0": {"precision": 0.0, "recall": 0.0, "f1-score": 0.0, "support": 0.0}, "0.25": {"precision": 0.0, "recall": 0.0, "f1-score": 0.0, "support": 0.0}, "0.5": {"precision": 0.0, "recall": 0.0, "f1-score": 0.0, "support": 0.0}, "1.0": {"precision": 0.0, "recall": 0.0, "f1-score": 0.0, "support": 8.0}, "1.75": {"precision": 0.0, "recall": 0.0, "f1-score": 0.0, "support": 0.0}, "accuracy": 0.0, "macro avg": {"precision": 0.0, "recall": 0.0, "f1-score": 0.0, "support": 8.0}, "weighted avg": {"precision": 0.0, "recall": 0.0, "f1-score": 0.0, "support": 8.0}}, "12.1_PE": {"0.0": {"precision": 0.0, "recall": 0.0, "f1-score": 0.0, "support": 0.0}, "0.5": {"precision": 0.0, "recall": 0.0, "f1-score": 0.0, "support": 1.0}, "0.75": {"precision": 0.0, "recall": 0.0, "f1-score": 0.0, "support": 2.0}, "1.0": {"precision": 0.0, "recall": 0.0, "f1-score": 0.0, "support": 11.0}, "accuracy": 0.0, "macro avg": {"precision": 0.0, "recall": 0.0, "f1-score": 0.0, "support": 14.0}, "weighted avg": {"precision": 0.0, "recall": 0.0, "f1-score": 0.0, "support": 14.0}}, "11.2_SDN": {"accuracy": 0.0, "macro avg": {"precision": NaN, "recall": NaN, "f1-score": NaN, "support": 0.0}, "weighted avg": {"precision": 0.0, "recall": 0.0, "f1-score": 0.0, "support": 0.0}}, "4.3": {"0.0": {"precision": 0.15, "recall": 1.0, "f1-score": 0.2608695652173913, "support": 3}, "0.5": {"precision": 0.0, "recall": 0.0, "f1-score": 0.0, "support": 4}, "1.0": {"precision": 0.0, "recall": 0.0, "f1-score": 0.0, "support": 13}, "accuracy": 0.15, "macro avg": {"precision": 0.049999999999999996, "recall": 0.3333333333333333, "f1-score": 0.08695652173913043, "support": 20}, "weighted avg": {"precision": 0.0225, "recall": 0.15, "f1-score": 0.03913043478260869, "support": 20}}, "10.3_TC": {"0.0": {"precision": 0.14285714285714285, "recall": 1.0, "f1-score": 0.25, "support": 1}, "0.125": {"precision": 0.0, "recall": 0.0, "f1-score": 0.0, "support": 0}, "0.5": {"precision": 0.0, "recall": 0.0, "f1-score": 0.0, "support": 1}, "0.75": {"precision": 0.0, "recall": 0.0, "f1-score": 0.0, "support": 5}, "1.0": {"precision": 0.0, "recall": 0.0, "f1-score": 0.0, "support": 1}, "accuracy": 0.125, "macro avg": {"precision": 0.02857142857142857, "recall": 0.2, "f1-score": 0.05, "support": 8}, "weighted avg": {"precision": 0.017857142857142856, "recall": 0.125, "f1-score": 0.03125, "support": 8}}, "2.3_DLL_v1.1": {"0.0": {"precision": 0.2222222222222222, "recall": 1.0, "f1-score": 0.3636363636363636, "support": 2}, "0.5": {"precision": 0.0, "recall": 0.0, "f1-score": 0.0, "support": 3}, "1.0": {"precision": 0.0, "recall": 0.0, "f1-score": 0.0, "support": 4}, "accuracy": 0.2222222222222222, "macro avg": {"precision": 0.07407407407407407, "recall": 0.3333333333333333, "f1-score": 0.1212121212121212, "support": 9}, "weighted avg": {"precision": 0.04938271604938271, "recall": 0.2222222222222222, "f1-score": 0.0808080808080808, "support": 9}}, "11.3_SDN": {"accuracy": 0.0, "macro avg": {"precision": NaN, "recall": NaN, "f1-score": NaN, "support": 0.0}, "weighted avg": {"precision": 0.0, "recall": 0.0, "f1-score": 0.0, "support": 0.0}}, "2.2_DLL": {"0.0": {"precision": 1.0, "recall": 1.0, "f1-score": 1.0, "support": 1}, "0.5": {"precision": 0.0, "recall": 0.0, "f1-score": 0.0, "support": 0}, "1.0": {"precision": 1.0, "recall": 0.18181818181818182, "f1-score": 0.3076923076923077, "support": 11}, "accuracy": 0.25, "macro avg": {"precision": 0.6666666666666666, "recall": 0.393939393939394, "f1-score": 0.4358974358974359, "support": 12}, "weighted avg": {"precision": 1.0, "recall": 0.25, "f1-score": 0.3653846153846154, "support": 12}}, "12.3_PE": {"0.0": {"precision": 0.14285714285714285, "recall": 0.5, "f1-score": 0.22222222222222224, "support": 2}, "0.5": {"precision": 0.0, "recall": 0.0, "f1-score": 0.0, "support": 0}, "0.75": {"precision": 0.0, "recall": 0.0, "f1-score": 0.0, "support": 5}, "1.0": {"precision": 0.0, "recall": 0.0, "f1-score": 0.0, "support": 7}, "accuracy": 0.07142857142857142, "macro avg": {"precision": 0.03571428571428571, "recall": 0.125, "f1-score": 0.05555555555555556, "support": 14}, "weighted avg": {"precision": 0.02040816326530612, "recall": 0.07142857142857142, "f1-score": 0.03174603174603175, "support": 14}}, "6.2_IPP": {"0.0": {"precision": 0.0, "recall": 0.0, "f1-score": 0.0, "support": 0}, "0.25": {"precision": 0.0, "recall": 0.0, "f1-score": 0.0, "support": 0}, "0.5": {"precision": 0.0, "recall": 0.0, "f1-score": 0.0, "support": 4}, "0.75": {"precision": 0.3333333333333333, "recall": 0.2, "f1-score": 0.25, "support": 5}, "1.0": {"precision": 0.0, "recall": 0.0, "f1-score": 0.0, "support": 10}, "accuracy": 0.05263157894736842, "macro avg": {"precision": 0.06666666666666667, "recall": 0.04, "f1-score": 0.05, "support": 19}, "weighted avg": {"precision": 0.08771929824561403, "recall": 0.05263157894736842, "f1-score": 0.06578947368421052, "support": 19}}, "1.6": {"0.0": {"precision": 0.0, "recall": 0.0, "f1-score": 0.0, "support": 2}, "0.5": {"precision": 0.0, "recall": 0.0, "f1-score": 0.0, "support": 1}, "1.0": {"precision": 1.0, "recall": 0.14285714285714285, "f1-score": 0.25, "support": 21}, "1.5": {"precision": 0.0, "recall": 0.0, "f1-score": 0.0, "support": 0}, "accuracy": 0.125, "macro avg": {"precision": 0.25, "recall": 0.03571428571428571, "f1-score": 0.0625, "support": 24}, "weighted avg": {"precision": 0.875, "recall": 0.125, "f1-score": 0.21875, "support": 24}}, "11.1_SDN": {"accuracy": 0.0, "macro avg": {"precision": NaN, "recall": NaN, "f1-score": NaN, "support": 0.0}, "weighted avg": {"precision": 0.0, "recall": 0.0, "f1-score": 0.0, "support": 0.0}}, "8.2_MM": {"0.0": {"precision": 0.09090909090909091, "recall": 1.0, "f1-score": 0.16666666666666669, "support": 1}, "0.375": {"precision": 0.0, "recall": 0.0, "f1-score": 0.0, "support": 2}, "0.625": {"precision": 0.0, "recall": 0.0, "f1-score": 0.0, "support": 1}, "0.75": {"precision": 0.0, "recall": 0.0, "f1-score": 0.0, "support": 4}, "0.875": {"precision": 0.0, "recall": 0.0, "f1-score": 0.0, "support": 1}, "1.0": {"precision": 0.0, "recall": 0.0, "f1-score": 0.0, "support": 4}, "accuracy": 0.07692307692307693, "macro avg": {"precision": 0.015151515151515152, "recall": 0.16666666666666666, "f1-score": 0.02777777777777778, "support": 13}, "weighted avg": {"precision": 0.006993006993006993, "recall": 0.07692307692307693, "f1-score": 0.012820512820512822, "support": 13}}, "6.3_IPP": {"0.0": {"precision": 0.0, "recall": 0.0, "f1-score": 0.0, "support": 0}, "0.25": {"precision": 0.0, "recall": 0.0, "f1-score": 0.0, "support": 2}, "0.5": {"precision": 0.75, "recall": 0.6, "f1-score": 0.6666666666666665, "support": 5}, "1.0": {"precision": 1.0, "recall": 0.3, "f1-score": 0.4615384615384615, "support": 10}, "1.5": {"precision": 0.0, "recall": 0.0, "f1-score": 0.0, "support": 0}, "2.0": {"precision": 0.0, "recall": 0.0, "f1-score": 0.0, "support": 0}, "accuracy": 0.35294117647058826, "macro avg": {"precision": 0.2916666666666667, "recall": 0.15, "f1-score": 0.188034188034188, "support": 17}, "weighted avg": {"precision": 0.8088235294117647, "recall": 0.35294117647058826, "f1-score": 0.46757164404223217, "support": 17}}, "5.7": {"0.0": {"precision": 0.0, "recall": 0.0, "f1-score": 0.0, "support": 0.0}, "0.375": {"precision": 0.0, "recall": 0.0, "f1-score": 0.0, "support": 3.0}, "0.5": {"precision": 0.0, "recall": 0.0, "f1-score": 0.0, "support": 0.0}, "0.625": {"precision": 0.0, "recall": 0.0, "f1-score": 0.0, "support": 2.0}, "0.75": {"precision": 0.0, "recall": 0.0, "f1-score": 0.0, "support": 4.0}, "1.0": {"precision": 0.0, "recall": 0.0, "f1-score": 0.0, "support": 5.0}, "1.25": {"precision": 0.0, "recall": 0.0, "f1-score": 0.0, "support": 0.0}, "1.75": {"precision": 0.0, "recall": 0.0, "f1-score": 0.0, "support": 0.0}, "accuracy": 0.0, "macro avg": {"precision": 0.0, "recall": 0.0, "f1-score": 0.0, "support": 14.0}, "weighted avg": {"precision": 0.0, "recall": 0.0, "f1-score": 0.0, "support": 14.0}}, "1.2": {"accuracy": 0.0, "macro avg": {"precision": NaN, "recall": NaN, "f1-score": NaN, "support": 0.0}, "weighted avg": {"precision": 0.0, "recall": 0.0, "f1-score": 0.0, "support": 0.0}}, "4.2_LM_v1.0": {"0.0": {"precision": 0.2, "recall": 1.0, "f1-score": 0.33333333333333337, "support": 1}, "0.5": {"precision": 0.0, "recall": 0.0, "f1-score": 0.0, "support": 0}, "0.75": {"precision": 0.0, "recall": 0.0, "f1-score": 0.0, "support": 0}, "1.0": {"precision": 0.0, "recall": 0.0, "f1-score": 0.0, "support": 13}, "accuracy": 0.07142857142857142, "macro avg": {"precision": 0.05, "recall": 0.25, "f1-score": 0.08333333333333334, "support": 14}, "weighted avg": {"precision": 0.014285714285714287, "recall": 0.07142857142857142, "f1-score": 0.02380952380952381, "support": 14}}}